{
	"schemaVersion": 1,
	"id": "pak",
	"version": "${version}",
	"name": "pak",
	"description": "Adds translations for paxynyae to minecraft",
	"authors": [
		"pero-sk"
	],
	"contact": {
		"homepage": "https://fabricmc.net/",
		"sources": "https://github.com/pero-sk/paxynyae"
	},
	"license": "CC0-1.0",
	"icon": "assets/pak/pax_icon.png",
	"environment": "*",
	"entrypoints": {
		"main": [
			"penguin.pak.Pak"
		],
		"client": [
			"penguin.pak.client.PakClient"
		]
	},
	"mixins": [
		"pak.${mc_version_tag}.mixins.json"
	],
	"depends": {
		"fabricloader": ">=${loader_version}",
		"minecraft": "~${minecraft_version}",
		"java": ">=21",
		"fabric-api": "*"
	}
}